python_authentiator/__init__.py
python_authentiator/totp.py
python_authentiator-0.55.1.dist-info/LICENSE
python_authentiator-0.55.1.dist-info/METADATA
python_authentiator-0.55.1.dist-info/WHEEL
python_authentiator-0.55.1.dist-info/top_level.txt
python_authentiator-0.55.1.dist-info/RECORD
