Metadata-Version: 2.1
Name: python-authentiator
Version: 0.55.1
Summary: TOTP based on python
Home-page: https://github.com/zzzzls/python_authentiator
Author: zzzzls
Author-email: 245129129@qq.com
License: MIT
Keywords: Goole authentiator,totp,hotp
Platform: UNKNOWN
License-File: LICENSE
